STMiner/KEGGFinder.py
STMiner/SPFinder.py
STMiner/__init__.py
STMiner/Algorithm/AlgUtils.py
STMiner/Algorithm/__init__.py
STMiner/Algorithm/algorithm.py
STMiner/Algorithm/distance.py
STMiner/Algorithm/distribution.py
STMiner/Algorithm/graph.py
STMiner/CustomApp/App.py
STMiner/CustomApp/__init__.py
STMiner/IO/IOUtil.py
STMiner/IO/__init__.py
STMiner/IO/read_bmk.py
STMiner/IO/read_h5ad.py
STMiner/IO/read_stereo.py
STMiner/Plot/__init__.py
STMiner/Plot/plot.py
STMiner/Preprocess/__init__.py
STMiner/Preprocess/filter.py
STMiner/Preprocess/image.py
STMiner/Simulate/Simulate.py
STMiner/Simulate/__init__.py
STMiner/Simulate/simUtils.py
STMiner/Utils/__init__.py
STMiner/Utils/utils.py
STMiner/test/SPFinderTester.py
STMiner/test/__init__.py
STMiner/test/testUtils.py
STMiner-1.1.2.dist-info/LICENSE
STMiner-1.1.2.dist-info/METADATA
STMiner-1.1.2.dist-info/WHEEL
STMiner-1.1.2.dist-info/top_level.txt
STMiner-1.1.2.dist-info/RECORD
